comfoair/__init__.py
comfoair/async_api.py
comfoair/model.py
comfoair-0.0.3.dist-info/METADATA
comfoair-0.0.3.dist-info/WHEEL
comfoair-0.0.3.dist-info/licenses/LICENSE
comfoair-0.0.3.dist-info/RECORD
