Metadata-Version: 2.4
Name: comfoair
Version: 0.0.3
Summary: Interface for Zehnder ComfoAir 350 ventilation units
Project-URL: Homepage, https://github.com/sim0nx/pycomfoair2
Project-URL: Source, https://github.com/sim0nx/pycomfoair2
Project-URL: Tracker, https://github.com/sim0nx/pycomfoair2/issues
Author-email: Andreas Oberritter <obi@saftware.de>, Georges Toth <georges@trypill.org>
License-Expression: MIT
License-File: LICENSE
Classifier: Intended Audience :: Developers
Classifier: Topic :: Home Automation
Requires-Python: >=3.13
Requires-Dist: async-timeout~=4.0
Requires-Dist: bitstring~=3.1
Requires-Dist: pyserial-asyncio-fast~=0.14
